continuationmonad/__init__.py
continuationmonad/abc.py
continuationmonad/exceptions.py
continuationmonad/py.typed
continuationmonad/typing.py
continuationmonad/continuationmonad/__init__.py
continuationmonad/continuationmonad/continuationmonad.py
continuationmonad/continuationmonad/from_.py
continuationmonad/continuationmonad/init.py
continuationmonad/continuationmonad/init.pyi
continuationmonad/continuationmonad/to.py
continuationmonad/continuationmonadtree/__init__.py
continuationmonad/continuationmonadtree/deferredhandler.py
continuationmonad/continuationmonadtree/init.py
continuationmonad/continuationmonadtree/init.pyi
continuationmonad/continuationmonadtree/nodes.py
continuationmonad/continuationmonadtree/observer.py
continuationmonad/continuationmonadtree/subscribeargs.py
continuationmonad/continuationmonadtree/to.py
continuationmonad/continuationmonadtree/operations/__init__.py
continuationmonad/continuationmonadtree/operations/connect.py
continuationmonad/continuationmonadtree/operations/defer.py
continuationmonad/continuationmonadtree/operations/flatmap.py
continuationmonad/continuationmonadtree/operations/map.py
continuationmonad/continuationmonadtree/operations/zip.py
continuationmonad/continuationmonadtree/sources/__init__.py
continuationmonad/continuationmonadtree/sources/error.py
continuationmonad/continuationmonadtree/sources/fromvalue.py
continuationmonad/continuationmonadtree/sources/gettrampoline.py
continuationmonad/continuationmonadtree/sources/scheduleabsolute.py
continuationmonad/continuationmonadtree/sources/scheduleon.py
continuationmonad/continuationmonadtree/sources/schedulerelative.py
continuationmonad/scheduler/__init__.py
continuationmonad/scheduler/cancellation.py
continuationmonad/scheduler/continuationcertificate.py
continuationmonad/scheduler/init.py
continuationmonad/scheduler/instantscheduler.py
continuationmonad/scheduler/instantscheduler.pyi
continuationmonad/scheduler/mainschedulermixin.py
continuationmonad-0.0.3.dist-info/METADATA
continuationmonad-0.0.3.dist-info/WHEEL
continuationmonad-0.0.3.dist-info/licenses/LICENCE
continuationmonad-0.0.3.dist-info/RECORD
