Metadata-Version: 2.4
Name: continuationmonad
Version: 0.0.3
Summary: A library that encapsulates callback functions within a continuation monad, utilizing a trampoline scheduler to enable stack-safe computations.
Project-URL: Homepage, https://github.com/MichaelSchneeberger/continuationmonad
Author-email: Michael Schneeberger <michael.schneeb@hotmail.com>
License-File: LICENCE
Requires-Python: >=3.12
Requires-Dist: dataclassabc>=0.0.15
